pippt/__init__.py
pippt/add_slide.py
pippt/add_split_slide.py
pippt/add_title_slide.py
pippt/pippt.py
pippt/data/code.dat
pippt/data/image.dat
pippt/data/sample.dat
pippt/script/pippt_script.py
pippt-2.5.0.dist-info/LICENSE.txt
pippt-2.5.0.dist-info/METADATA
pippt-2.5.0.dist-info/WHEEL
pippt-2.5.0.dist-info/entry_points.txt
pippt-2.5.0.dist-info/top_level.txt
pippt-2.5.0.dist-info/RECORD
