Metadata-Version: 2.1
Name: pippt
Version: 2.5.0
Summary: A simple presentation module
Home-page: https://github.com/Ideas100/Pi-ppt
Author: Pravin Raghul
Author-email: pravinraghul@gmail.com
License: MIT
Platform: UNKNOWN
Classifier: Intended Audience :: Developers
Classifier: License :: OSI Approved :: MIT License
Classifier: Operating System :: OS Independent
Classifier: Programming Language :: Python :: 3.8
Requires-Dist: Pillow
